authenticate_user/__init__.py
authenticate_user/authentication_api.py
security_manager_apis/__init__.py
security_manager_apis/application.properties
security_manager_apis/get_properties_data.py
security_manager_apis/orchestration_apis.py
security_manager_apis/policy_optimizer.py
security_manager_apis/policy_planner.py
security_manager_apis/security_manager.py
security_manager_apis-1.0.1.dist-info/LICENSE
security_manager_apis-1.0.1.dist-info/METADATA
security_manager_apis-1.0.1.dist-info/WHEEL
security_manager_apis-1.0.1.dist-info/top_level.txt
security_manager_apis-1.0.1.dist-info/RECORD
