Metadata-Version: 2.1
Name: security-manager-apis
Version: 1.0.1
Summary: Security Manager API
Home-page: 
Author-email: bryan.ellis@firemon.com
Project-URL: Documentation, https://github.com/bellist/pythonSDK/blob/main/README.md
Project-URL: GitHub, https://github.com/bellist/pythonSDK
Project-URL: Changelog, https://github.com/bellist/pythonSDK/blob/main/CHANGELOG.md
Keywords: Security Manager APIs
Requires-Python: >=3.6
License-File: LICENSE
Requires-Dist: requests (>=2.20.1)
